loadguard/__init__.py
loadguard/consts.py
loadguard/main.py
loadguard/stores.py
loadguard/plugins/__init__.py
loadguard/project/__init__.py
loadguard/runner/__init__.py
loadguard/scenarii/__init__.py
loadguard/scenarii/base.py
loadguard/scenarii/replay.py
loadguard/scenarii/scenario.py
loadguard/scenarii/scenario_http.py
loadguard/templates/__init__.py
loadguard/templates/manager.py
loadguard_runner-0.0.5.5.dist-info/LICENSE
loadguard_runner-0.0.5.5.dist-info/METADATA
loadguard_runner-0.0.5.5.dist-info/WHEEL
loadguard_runner-0.0.5.5.dist-info/top_level.txt
loadguard_runner-0.0.5.5.dist-info/RECORD
