Metadata-Version: 2.1
Name: loadguard-runner
Version: 0.0.5.5
Summary: An agnostic runner for automation of common tasks related to the performance test execution process.
Home-page: https://github.com/loadguard/runner
Author: The Deepnox team
Author-email: contact@deepnox.io
License: Copyrighted 2021, Deepnox SAS
Download-URL: https://github.com/loadguard/runner/0.0.5.5.tar.gz
Keywords: deepnox,load,performance,testing,test
Platform: UNKNOWN
Classifier: Development Status :: 2 - Pre-Alpha
Classifier: Topic :: Software Development :: Testing
Classifier: Topic :: Software Development :: Testing :: Traffic Generation
Classifier: License :: OSI Approved :: MIT License
Classifier: Programming Language :: Python :: 3.9
License-File: LICENSE
Requires-Dist: future (~=0.18.2)
Requires-Dist: python-dateutil (~=2.8.1)
Requires-Dist: urllib3 (~=1.25.7)
Requires-Dist: wipbox (==0.0.14.1)
